markdown2code/__init__.py
markdown2code/__main__.py
markdown2code/backup.py
markdown2code/cli.py
markdown2code/config.py
markdown2code/converter.py
markdown2code/converter/__init__.py
markdown2code/converter/constants.py
markdown2code/converter/core.py
markdown2code/converter/file_utils.py
markdown2code/converter/markdown_utils.py
markdown2code/web/__init__.py
markdown2code/web/server.py
markdown2code-2.8.0.dist-info/LICENSE
markdown2code-2.8.0.dist-info/METADATA
markdown2code-2.8.0.dist-info/WHEEL
markdown2code-2.8.0.dist-info/entry_points.txt
markdown2code-2.8.0.dist-info/top_level.txt
markdown2code-2.8.0.dist-info/RECORD
