Metadata-Version: 2.1
Name: markdown2code
Version: 2.8.0
Summary: Convert markdown files into organized project structures with code files
Home-page: https://github.com/plain-mark/markdown2code
Author: Tom Sapletta
Author-email: info@softreck.dev
License: Apache
Keywords: markdown,code generation,project structure,development tools
Classifier: Development Status :: 4 - Beta
Classifier: Intended Audience :: Developers
Classifier: Topic :: Software Development :: Build Tools
Classifier: Topic :: Software Development :: Code Generators
Classifier: Topic :: Text Processing :: Markup :: Markdown
Classifier: Programming Language :: Python :: 3
Classifier: Programming Language :: Python :: 3.6
Classifier: Programming Language :: Python :: 3.7
Classifier: Programming Language :: Python :: 3.8
Classifier: Programming Language :: Python :: 3.9
Classifier: Programming Language :: Python :: 3.10
Classifier: Programming Language :: Python :: 3.11
Classifier: License :: OSI Approved :: Apache Software License
Classifier: Operating System :: OS Independent
Requires-Python: >=3.6
License-File: LICENSE
Requires-Dist: pathlib>=1.0.1
Requires-Dist: PyYAML>=6.0.0
Requires-Dist: Flask>=2.3.3
